<ImportMXDLog>	<Messages>
		<FileName>C:\GIS_Tools\Engineering_Tools\Blank_Template_10.7.1.mxd</FileName>
		<Message>
			<Name></Name>
			<MessageType>Error</MessageType>
			<Severity>High</Severity>
			<Description>Data frame does not have layers</Description>
			<Code>00001</Code>
			<ComponentName>Layers</ComponentName>
			<ComponentType>Map</ComponentType>
</Message>
		<Message>
			<Name></Name>
			<MessageType>Error</MessageType>
			<Severity>High</Severity>
			<Description>Data frame does not have a spatial reference</Description>
			<Code>00002</Code>
			<ComponentName>Layers</ComponentName>
			<ComponentType>Map</ComponentType>
</Message>
		<Message>
			<Name></Name>
			<MessageType>Warning</MessageType>
			<Severity>Medium</Severity>
			<Description>Neatlines were converted to rectangles.</Description>
			<Code>20041</Code>
			<ComponentName>Blank_Template_10.7.1</ComponentName>
			<ComponentType>Layout</ComponentType>
</Message>
		<Message>
			<Name></Name>
			<MessageType>Warning</MessageType>
			<Severity>Medium</Severity>
			<Description>Legends imported into ArcGIS Pro may appear differently due to improvements in the fitting strategy and changes made to legend patch shapes. Modifications to the default appearance may be required.</Description>
			<Code>20038</Code>
			<ComponentName>Blank_Template_10.7.1</ComponentName>
			<ComponentType>Layout</ComponentType>
</Message>
</Messages>
</ImportMXDLog>